Workbook

Sheet Read Me
A1: PROTOPUS — economics model behind the murder-board answers (2 Oct 2026)
A3: How to use
A4: • Blue numbers are inputs. Change them and every black formula recalculates. Yellow cells are the key levers.
A5: • Green numbers pull from the Assumptions sheet.
A6: • 'Payback' answers Prateek's question: if Baker costs ₹X lakh, how many boards before it pays for itself? Edit Assumptions!C6.
A7: • USD converted at ₹88, the rate used in the 29 Sep cost report, so every figure here matches that report.
A9: Where the numbers come from
A10: • Build costs: Protopus Cost Report (29 Sep 2026). Baker prototype ₹3,73,418; Mixer prototype ₹74,847; Baker production ₹1,44,842; Mixer production ₹13,740.
A11: • Consumable prices: prototype BOM listings (FR4 ₹99, LPSM ₹1,100/kg, Sn42Bi58 ₹1,500/500 g, TR300 ₹7,500/kg, V-bits $23.99/10). Usage per board is our engineering estimate.
A12: • JLCPCB prices: jlcpcb.com ($2 for 5 PCBs; PCBA $8 setup, $1.50 stencil, $0.0017/joint). Shipping and duty to India: zbotic.in guide (DHL $25–45, 10% BCD + 18% IGST, 7–20 days door to door).
A13: • Indian rush fab: zbotic.in (₹3,000–8,000 for 5 two-layer boards in 24 h).
A14: • Competitor prices: see the Competitors sheet, one source per row.
... A20: • Duty, freight and China turnkey prices still need a customs broker and supplier quotes.

Sheet Assumptions
A1: Assumptions (inputs in blue)
A3: Item | B3: Unit | C3: Value | D3: Source / note
A4: USD → INR | B4: ₹/$ | C4: 88 | D4: Rate used in the 29 Sep 2026 cost report
A5: Baker production cost (China parts, Delhi build, 100-unit batch) | B5: ₹ | C5: 144842 | D5: Cost Report 29 Sep 2026, p.3
A6: Baker selling price (ex-GST) | B6: ₹ | C6: 299000 | D6: Deck price (projected). Edit this cell to test ₹X lakh
A7: Mixer production cost | B7: ₹ | C7: 13740 | D7: Cost Report 29 Sep 2026, p.4
A8: Mixer selling price (ex-GST) | B8: ₹ | C8: 34999 | D8: Deck price (projected)
A9: Baker prototype build cost | B9: ₹ | C9: 373418 | D9: Cost Report 29 Sep 2026, p.1 (incl. 35% duty/courier on imports + 15% contingency)
A10: Mixer prototype build cost | B10: ₹ | C10: 74847 | D10: Cost Report 29 Sep 2026, p.2
A11: Proto plan | B11: ₹/year | C11: 9999 | D11: Deck price: one Proto plan per workspace (planned)
A12: Consumable kit price per board | B12: ₹ | C12: 699 | D12: PROPOSED (FR4, mask, paste, film, jig resin)
A13: Board iterations per week, startup customer | B13: #/wk | C13: 2 | D13: ASSUMPTION for payback illustration
A14: Board iterations per week, college lab | B14: #/wk | C14: 1 | D14: ASSUMPTION for payback illustration
A15: Working weeks per year | B15: # | C15: 48 | D15: ASSUMPTION
... A18: Indian rush fab, 5 bare 2-layer boards (high) | B18: ₹ | C18: 8000 | D18: zbotic.in rush-prototyping guide

Sheet Unit Economics
A1: Unit economics per machine
A3: Line | B3: Baker | C3: Mixer | D3: Bundle | E3: Note
A4: Selling price (ex-GST) | B4: =Assumptions!C6 -> 299000 | C4: =Assumptions!C8 -> 34999 | D4: =B4+C4 -> 333999
A5: Production cost (landed, built in Delhi) | B5: =Assumptions!C5 -> 144842 | C5: =Assumptions!C7 -> 13740 | D5: =B5+C5 -> 158582 | E5: China turnkey quotes pending (RFQ at 5–5,000 units)
A6: Gross profit per unit | B6: =B4-B5 -> 154158 | C6: =C4-C5 -> 21259 | D6: =D4-D5 -> 175417
A7: Gross margin | B7: =IF(B4=0,0,B6/B4) -> 0.5155786 | C7: =IF(C4=0,0,C6/C4) -> 0.60741735 | D7: =IF(D4=0,0,D6/D4) -> 0.52520217
A8: Price ÷ cost | B8: =IF(B5=0,0,B4/B5) -> 2.0643184 | C8: =IF(C5=0,0,C4/C5) -> 2.5472344 | D8: =IF(D5=0,0,D4/D5) -> 2.1061596
A11: Baker price sensitivity
A12: Baker price (ex-GST) | B12: Gross margin | C12: Bundle price | D12: Break-even iterations vs JLCPCB | E12: Note
A13: 299000 | B13: =(A13-Assumptions!$C$5)/A13 -> 0.5155786 | C13: =A13+Assumptions!$C$8 -> 333999 | D13: =ROUNDUP(C13/'Board Cost'!$C$27,0) -> 53 | E13: Deck price
A14: 349000 | B14: =(A14-Assumptions!$C$5)/A14 -> 0.58497994 | C14: =A14+Assumptions!$C$8 -> 383999 | D14: =ROUNDUP(C14/'Board Cost'!$C$27,0) -> 61
A15: 399000 | B15: =(A15-Assumptions!$C$5)/A15 -> 0.63698747 | C15: =A15+Assumptions!$C$8 -> 433999 | D15: =ROUNDUP(C15/'Board Cost'!$C$27,0) -> 68
A16: 449000 | B16: =(A16-Assumptions!$C$5)/A16 -> 0.67741203 | C16: =A16+Assumptions!$C$8 -> 483999 | D16: =ROUNDUP(C16/'Board Cost'!$C$27,0) -> 76
A19: Recurring revenue per installed Baker (after year 1)
A20: Line | B20: Revenue ₹/yr | C20: Cost ₹/yr | D20: Gross profit ₹/yr | E20: Note
A21: Proto plan | B21: =Assumptions!C11 -> 9999 | C21: 0 | D21: =B21-C21 -> 9999 | E21: Cloud/LLM cost per lab not yet measured; set C21 once known
A22: Consumable kits | B22: =Assumptions!C12*Assumptions!C16 -> 104850 | C22: ='Board Cost'!C16*Assumptions!C16 -> 50028.36 | D22: =B22-C22 -> 54821.64
A23: Total | B23: =B21+B22 -> 114849 | C23: =C21+C22 -> 50028.36 | D23: =D21+D22 -> 64820.64

Sheet Board Cost
A1: What one prototype board costs: Baker vs ordering it
A3: A. Baker consumables per 100 × 160 mm board (components excluded)
A4: Item | B4: Pack price ₹ | C4: Per board ₹ | D4: Basis
A5: FR4 copper-clad 100×150 mm | B5: 99 | C5: =B5 -> 99 | D5: Listing ₹99 each (1 per board)
A6: Alkali-developing LPSM solder mask | B6: 1100 | C6: =B6/1000*3 -> 3.3 | D6: ₹1,100/kg; ~3 g per board incl. waste (est.)
A7: Sodium carbonate developer | B7: 200 | C7: 1 | D7: Few mL of dilute solution (est.)
A8: Sn42Bi58 low-temp paste | B8: 1500 | C8: =B8/500*1.5 -> 4.5 | D8: ₹1,500/500 g; ~1.5 g per board (est.)
A9: Polyimide stencil film | B9: 3150 | C9: 25 | D9: Roll ₹3,150; ~₹25 of film per board (est.)
A10: TR300 high-temp resin (placement jig) | B10: 7500 | C10: =B10/1000*15 -> 112.5 | D10: ₹7,500/kg; ~15 g jig (est.)
A11: IPA for jig wash | B11: 200 | C11: =B11/1000*20 -> 4 | D11: ₹200/L; ~20 mL (est.)
A12: V-bit wear | B12: =23.99*Assumptions!C4/10 -> 211.112 | C12: =B12/5 -> 42.2224 | D12: $23.99 per 10 bits; ~5 boards per bit (est.)
A13: Drill wear | B13: 1500 | C13: =B13/50 -> 30 | D13: ₹1,500 set; ~50 boards per set (est.)
A14: Electricity | B14: 8 | C14: =B14*1.5 -> 12 | D14: ₹8/kWh; ~1.5 kWh per board (est.)
A16: Baker consumables per board | C16: =SUM(C5:C14) -> 333.5224
A18: B. Same board ordered from JLCPCB to India (assembled, components excluded)
A19: Item | B19: USD | C19: ₹ | D19: Basis
A20: PCB, 5 pcs, 100×160 mm (over the $2 ≤100×100 tier) | B20: 5 | C20: =B20*Assumptions!$C$4 -> 440 | D20: Estimate; $2 applies only up to 100×100 mm
A21: PCBA setup fee | B21: 8 | C21: =B21*Assumptions!$C$4 -> 704 | D21: jlcpcb.com PCBA pricing
A22: Stencil | B22: 1.5 | C22: =B22*Assumptions!$C$4 -> 132 | D22: jlcpcb.com PCBA pricing
A23: SMT joints (200 × $0.0017) | B23: =200*0.0017 -> 0.34 | C23: =B23*Assumptions!$C$4 -> 29.92 | D23: jlcpcb.com PCBA pricing
A24: Extended-part loading fees (3 × $3) | B24: 9 | C24: =B24*Assumptions!$C$4 -> 792 | D24: ASSUMPTION: 3 non-basic parts
A25: DHL/UPS express to India | B25: 35 | C25: =B25*Assumptions!$C$4 -> 3080 | D25: Midpoint of $25–45 (zbotic.in)
A26: Customs: 10% BCD + 18% IGST on (value + BCD) | C26: =SUM(C20:C25)*((1+0.1)*(1+0.18)-1) -> 1543.0202 | D26: Effective 29.8%. IGST can be claimed back if GST-registered; BCD cannot.
A27: Saving per iteration with Baker (JLCPCB total − Baker consumables) | C27: =SUM(C20:C26)-C16 -> 6387.4178
A28: JLCPCB assembled iteration, landed in India | C28: =SUM(C20:C26) -> 6720.9402 | D28: Door-to-door 7–20 days (fab + DHL + customs)
A30: C. Indian 24-hour fab (bare boards only; assembly extra)
A31: Midpoint of ₹3,000–8,000 for 5 boards | C31: =(Assumptions!C17+Assumptions!C18)/2 -> 5500
A32: Saving per iteration vs Baker (bare board only; conservative) | C32: =C31-C16 -> 5166.4776

Sheet Payback
A1: Does Baker pay for itself? (Prateek: 'Say X lacs...')
A3: Line | B3: vs JLCPCB to India | C3: vs Indian 24-h fab | D3: Note
A4: Customer spend: Baker + Mixer (ex-GST) | B4: ='Unit Economics'!D4 -> 333999 | C4: ='Unit Economics'!D4 -> 333999
A5: Direct saving per board iteration | B5: ='Board Cost'!C27 -> 6387.4178 | C5: ='Board Cost'!C32 -> 5166.4776 | D5: Engineer time and waiting days not counted
A6: Break-even iterations | B6: =IF(B5<=0,0,ROUNDUP(B4/B5,0)) -> 53 | C6: =IF(C5<=0,0,ROUNDUP(C4/C5,0)) -> 65
A7: Months to break even, startup (Assumptions!C13 per week) | B7: =B6/(Assumptions!$C$13*Assumptions!$C$15/12) -> 6.625 | C7: =C6/(Assumptions!$C$13*Assumptions!$C$15/12) -> 8.125
A8: Months to break even, college lab (Assumptions!C14 per week) | B8: =B6/(Assumptions!$C$14*Assumptions!$C$15/12) -> 13.25 | C8: =C6/(Assumptions!$C$14*Assumptions!$C$15/12) -> 16.25
A10: Calendar time per iteration
A11: Route | B11: Door-to-door | C11: Hands-on | D11: Source
A12: JLCPCB → India (DHL) | B12: 7–20 days | C12: Order + customs paperwork | D12: zbotic.in
A13: Indian rush fab (bare boards) | B13: 24–48 h + courier | C13: Stencil + hand assembly extra | D13: zbotic.in
A14: Baker (target, to be measured in Phase 1) | B14: ≈1.5–2.5 h | C14: ≈15–25 min | D14: Throughput sheet
A16: Baker-first: customer spend, Baker only (ex-GST) | B16: ='Unit Economics'!B4 -> 299000 | C16: ='Unit Economics'!B4 -> 299000 | D16: Phase 1 sells Baker + Proto; Mixer follows
A17: Baker-first: break-even iterations | B17: =IF(B5<=0,0,ROUNDUP(B16/B5,0)) -> 47 | C17: =IF(C5<=0,0,ROUNDUP(C16/C5,0)) -> 58
A18: Baker-first: months to break even, startup | B18: =B17/(Assumptions!$C$13*Assumptions!$C$15/12) -> 5.875 | C18: =C17/(Assumptions!$C$13*Assumptions!$C$15/12) -> 7.25
A19: Baker-first: months to break even, college lab | B19: =B17/(Assumptions!$C$14*Assumptions!$C$15/12) -> 11.75 | C19: =C17/(Assumptions!$C$14*Assumptions!$C$15/12) -> 14.5

Sheet Throughput & Scale
A1: Cycle time per board (engineering targets, not yet measured)
A3: Step | B3: Low min | C3: High min | D3: Hands-on? | E3: Note
A4: 01 Load + 02 probe height map | B4: 5 | C4: 5 | D4: Yes (load) | E4: Magazine feed; operator refills
A5: 03 Isolation mill | B5: 25 | C5: 45 | D5: No | E5: Depends on copper area and trace count
A6: 03 Drill | B6: 5 | C6: 10 | D6: No | E6: ~50 holes
A7: 04 Vacuum clean | B7: 2 | C7: 2 | D7: No
A8: 06 Coat mask | B8: 3 | C8: 5 | D8: No | E8: Syringe dispense
A9: 07 UV image (10.1 in LCD, 405 nm) | B9: 2 | C9: 4 | D9: No
A10: 08 Wipe-develop + air knife | B10: 4 | C10: 6 | D10: No
A11: 09 Flood cure | B11: 5 | C11: 10 | D11: No
A12: 10 Laser-cut stencil | B12: 5 | C12: 10 | D12: No
A13: 11–12 Clamp, paste, release | B13: 3 | C13: 3 | D13: No
A14: Placement jig print (parallel with 01–12) | B14: 0 | C14: 0 | D14: No | E14: 30–45 min incl. wash/cure; hidden behind steps 01–12
A15: 13 Manual placement (~40 parts, 10–20 s each) | B15: 7 | C15: 14 | D15: Yes | E15: Vacuum pen into printed jig
A16: 14 Reflow + cool | B16: 10 | C16: 12 | D16: No | E16: Sn42Bi58, 138 °C melt
A17: 15 Test on Mixer | B17: 5 | C17: 15 | D17: Yes (hook-up) | E17: Proto runs the test plan
A18: Total per board (minutes) | B18: =SUM(B4:B17) -> 81 | C18: =SUM(C4:C17) -> 141
A19: Total per board (hours) | B19: =B18/60 -> 1.35 | C19: =C18/60 -> 2.35
A21: Shift length (h) | B21: 8
A22: Working days per year | B22: 250
A23: Boards per shift (at slow and fast cycle) | B23: =ROUNDDOWN(B21*60/C18,0) -> 3 | C23: =ROUNDDOWN(B21*60/B18,0) -> 5
A24: Boards per year, one machine, one shift | B24: =B23*B22 -> 750 | C24: =C23*B22 -> 1250
A27: Prateek: '1,000 boards? 10,000? 1 lakh?'
A28: Boards per year | B28: Bakers needed (1 shift, slow cycle) | C28: Right tool | E28: Why
A29: 10 | B29: =ROUNDUP(A29/$B$24,0) -> 1 | C29: Baker | E29: Same-day iteration; fab minimums and shipping dominate
A30: 100 | B30: =ROUNDUP(A30/$B$24,0) -> 1 | C30: Baker | E30: One machine covers a busy lab or startup
A31: 1000 | B31: =ROUNDUP(A31/$B$24,0) -> 2 | C31: Baker for iterations; fab for identical batches | E31: 1–2 machines; any batch of >10 identical boards goes to a fab
A32: 10000 | B32: =ROUNDUP(A32/$B$24,0) -> 14 | C32: Fab / EMS | E32: Production. Proto exports the validated Gerber/BOM/CPL
A33: 100000 | B33: =ROUNDUP(A33/$B$24,0) -> 134 | C33: Fab / EMS | E33: Production. Baker is not built for this and we do not claim it

Sheet Use of Funds
A1: ₹15 lakh, proof of concept: Proto + Baker first (Mixer and Probe Matrix are step 2, after the PoC)
A3: Line | B3: ₹ | C3: Share | D3: Basis
A4: Baker prototype build (full BOM, duty, 15% contingency) | B4: 373418 | C4: =B4/$B$12 -> 0.24894533 | D4: Cost Report 29 Sep 2026; costing workbook
A5: Baker Rev B iteration (heads, fixture, film module, wiring) | B5: 100000 | C5: =B5/$B$12 -> 0.066666667 | D5: ASSUMPTION ≈ 32% of Baker parts
A6: PoC consumables (~150 test boards) | B6: 60000 | C6: =B6/$B$12 -> 0.04 | D6: FR4 ₹99/board + bits, resin, mask, paste, demo parts
A7: One software + firmware engineer, 9 months at ₹50,000 | B7: 450000 | C7: =B7/$B$12 -> 0.3 | D7: Costing workbook, PoC Budget
A8: Proto software + compute, 9 months at ₹15,000 | B8: 135000 | C8: =B8/$B$12 -> 0.09 | D8: LLM API + hosting (ASSUMPTION)
A9: Testing + tooling (reference instruments, laser power meter, hand tools) | B9: 100000 | C9: =B9/$B$12 -> 0.066666667 | D9: Plan
A10: Lab set-up + safety (ESD, fume extraction, fire safety) | B10: 50000 | C10: =B10/$B$12 -> 0.033333333 | D10: Plan; university lab, no rent
A11: IP + legal ₹75,000, demos/outreach ₹50,000, reserve ₹1,06,582 | B11: 231582 | C11: =B11/$B$12 -> 0.154388 | D11: Plan; reserve = ask − subtotal
A12: Total | B12: =SUM(B4:B11) -> 1500000 | C12: =SUM(C4:C11) -> 1
A13: No founder salary. Lean option if the round is capped at ₹10L: Baker ₹3.73L + Rev B ₹1.0L + engineer 6 months ₹3.0L + compute ₹0.9L + testing ₹1.0L = ₹9.63L + ₹0.37L reserve.

Sheet Competitors
A1: Competitor pricing (list prices, before Indian duty and GST)
A3: Product | B3: Category | C3: Low (USD) | D3: High (USD) | E3: Low (₹ at ₹88) | F3: What it does not do | G3: Source
A4: LPKF ProtoMat S104 line | B4: In-house PCB (pro) | C4: 96000 | D4: 96000 | E4: =IF(ISNUMBER(C4),C4*Assumptions!$C$4,"n/a") -> 8448000 | F4: Quote-only. $96k was a full S104 line bought new in 2019; separate machines for mask, plating, assembly | G4: exapro.com used listing
A5: Voltera NOVA | B5: Printed electronics | C5: 45974 | D5: 45974 | E5: =IF(ISNUMBER(C5),C5*Assumptions!$C$4,"n/a") -> 4045712 | F5: Ink on flexible substrates; not copper FR4 + test | G5: store.voltera.io
A6: Makera Carvera | B6: Desktop CNC | C6: 5499 | D6: 5499 | E6: =IF(ISNUMBER(C6),C6*Assumptions!$C$4,"n/a") -> 483912 | F6: Mills only; no mask, stencil, assembly or test | G6: Makera store, Oct 2026 ($5,499)
A7: Makera Carvera Air | B7: Desktop CNC | C7: 2499 | D7: 2499 | E7: =IF(ISNUMBER(C7),C7*Assumptions!$C$4,"n/a") -> 219912 | F7: Mills only | G7: Makera store, Oct 2026 ($2,499)
A8: BotFactory Squink | B8: Printed PCB + P&P | C8: 3199 | D8: 4499 | E8: =IF(ISNUMBER(C8),C8*Assumptions!$C$4,"n/a") -> 281512 | F8: Conductive ink; SV2 price on request | G8: techcrunch / BotFactory
A9: Bantam Tools PCB mill | B9: Desktop PCB mill | C9: n/a | D9: n/a | E9: =IF(ISNUMBER(C9),C9*Assumptions!$C$4,"n/a") -> n/a | F9: Product line discontinued; company now sells art machines | G9: toolguyd.com
A10: Neoden YY1 | B10: Pick-and-place only | C10: 3000 | D10: 3000 | E10: =IF(ISNUMBER(C10),C10*Assumptions!$C$4,"n/a") -> 264000 | F10: Places parts only; no board, no test | G10: EEVblog ('under $3K')
A11: Digilent Analog Discovery 3 | B11: USB instrument | C11: 389 | D11: 389 | E11: =IF(ISNUMBER(C11),C11*Assumptions!$C$4,"n/a") -> 34232 | F11: Human reads the screen; not tied to design files | G11: RS / RobotShop, Oct 2026 ($389)
A12: ADALM2000 | B12: USB instrument | C12: 237 | D12: 262 | E12: =IF(ISNUMBER(C12),C12*Assumptions!$C$4,"n/a") -> 20856 | F12: Same | G12: Mouser / Richardson RFPD
A13: Moku:Go M0–M2 | B13: USB instrument | C13: 599 | D13: 799 | E13: =IF(ISNUMBER(C13),C13*Assumptions!$C$4,"n/a") -> 52712 | F13: Same | G13: Liquid Instruments / TEquipment
A14: Red Pitaya STEMlab 125-14 | B14: FPGA instrument | C14: 490 | D14: 716 | E14: =IF(ISNUMBER(C14),C14*Assumptions!$C$4,"n/a") -> 43120 | F14: Same | G14: redpitaya.com
A15: Saleae Logic 8 / Pro 16 | B15: Logic analyser | C15: 499 | D15: 1499 | E15: =IF(ISNUMBER(C15),C15*Assumptions!$C$4,"n/a") -> 43912 | F15: Logic only | G15: saleae.com
A16: Rigol DHO804 | B16: Bench scope | C16: 492 | D16: 579 | E16: =IF(ISNUMBER(C16),C16*Assumptions!$C$4,"n/a") -> 43296 | F16: Scope only | G16: electro-meters.com
A17: Flux | B17: AI PCB design (SaaS) | C17: 15 | D17: 49 | E17: =IF(ISNUMBER(C17),C17*Assumptions!$C$4,"n/a") -> 1320 | F17: Per editor per month. Output stops at files | G17: flux.ai pricing
A19: PROTOPUS Baker + Mixer (deck price) | B19: Prototyping cell + AI | E19: ='Unit Economics'!D4 -> 333999 | F19: Board, mask, stencil, paste, reflow, test, driven by Proto

Sheet Market
A1: India beachhead, bottom-up (upper bound, one Baker + Mixer per buyer)
A3: Segment | B3: Buyers | C3: Hardware ₹ | D3: Source / assumption
A4: AICTE-approved engineering colleges | B4: 5868 | C4: =B4*'Unit Economics'!$D$4 -> 1959906132 | D4: educationforallinindia.com (AICTE count)
A5: Hardware-relevant startups (1% of 2.25 lakh DPIIT startups) | B5: =ROUND(225000*B8,0) -> 2250 | C5: =B5*'Unit Economics'!$D$4 -> 751497750 | D5: 2.25 lakh: TiE / DPIIT early 2026. 1% share is an ASSUMPTION
A6: Total one-time hardware pool | B6: =B4+B5 -> 8118 | C6: =C4+C5 -> 2711403882
A7: Baker-first pool (Baker only, step 1) | C7: =B6*'Unit Economics'!$B$4 -> 2427282000
A8: Hardware-relevant share of DPIIT startups | B8: 0.01
A9: Recurring Proto plan pool per year (₹9,999/yr × all buyers above) | C9: =B6*Assumptions!C11 -> 81171882
A11: Context numbers (not in the sum)
A12: Atal Tinkering Labs set up (schools) | B12: 10000 | D12: AIM/PIB 2025: 722 districts, 1.1 crore students
A13: New ATLs announced for the next 5 years | B13: 50000 | D13: Union Budget 2025-26
A14: ATL grant per school (₹) | B14: 2000000 | D14: AIM: ₹10 lakh setup + ₹10 lakh O&M over 5 years
A15: B.Tech students enrolled | B15: 2320000 | D15: AISHE, 23.2 lakh
A16: C2S academic institutions + DLI startups | B16: 400 | D16: MeitY/PIB: 305 + 95
A17: Fab Labs worldwide | B17: 2300 | D17: Fab Foundation: 2,300+ (other counts 2,700+)
